{
    "keep": {
        "days": true,
        "amount": 14
    },
    "auditLog": "F:\\projects\\university-management-auth\\logs\\winston\\succeses\\.9d3dfce6b6efb71cb8264cbc7fa0b9de7a7aab24-audit.json",
    "files": [
        {
            "date": 1688210158018,
            "name": "F:\\projects\\university-management-auth\\logs\\winston\\succeses\\phu-2023-07-01-success.log",
            "hash": "fa57d5fdf5dca8abea610e91053041e8d7ae9a84932bb4852526f7c51258c514"
        },
        {
            "date": 1688279907415,
            "name": "F:\\projects\\university-management-auth\\logs\\winston\\succeses\\phu-2023-07-02-success.log",
            "hash": "678ae31abee0f24d27cd2794f3b37f8b3962b47dc6b08d6dc279bec28de74011"
        }
    ],
    "hashType": "sha256"
}